climate_analyzer/__init__.py
climate_analyzer/_mpl_tk.py
climate_analyzer/cda.py
climate_analyzer/climate_dataobj.py
climate_analyzer/db_coupler.py
climate_analyzer/fips2db.py
climate_analyzer/gui_main.py
climate_analyzer/gui_plot.py
climate_analyzer/gui_style.py
climate_analyzer/noaa.py
climate_analyzer/extra/arrow-lf16x16.gif
climate_analyzer/extra/arrow-rt16x16.gif
climate_analyzer/extra/fips_codes.db
climate_analyzer-0.1.0.dist-info/METADATA
climate_analyzer-0.1.0.dist-info/WHEEL
climate_analyzer-0.1.0.dist-info/entry_points.txt
climate_analyzer-0.1.0.dist-info/licenses/LICENSE
climate_analyzer-0.1.0.dist-info/RECORD
