Metadata-Version: 2.1
Name: climate_analyzer
Version: 0.1.0
Summary: Download & Analyze NOAA Climate Data
Project-URL: Homepage, https://github.com/cagledw/climate_analyzer
Author-email: David Cagle <davidc@clearfocusengineering.com>
License-File: LICENSE
Classifier: License :: OSI Approved :: MIT License
Classifier: Operating System :: OS Independent
Classifier: Programming Language :: Python :: 3
Requires-Python: >=3.7
Requires-Dist: haversine>=2.7.0
Requires-Dist: matplotlib>=3.5.1
Requires-Dist: numpy>=1.23.5
Requires-Dist: requests>=2.26.0
